<detall><id label=""><![CDATA[102136]]></id><title label="Titol"><![CDATA[The music collectors' event]]></title><excerpt label="Resum"><![CDATA[<strong>Fairs.</strong> Lovers of musical treasures should not miss the event at Cotxeres de Sants this weekend.]]></excerpt><content label="Contingut"><![CDATA[<p>For the sixteenth year running, the Record Collectors&#8217; Fair will be held, where collectors can bring their records, cds, merchandising, books, music dvds and all items related to the world of music to sell or exchange with other collectors who cannot attend the major fairs.</p>
<p>The event is held at Cotxeres de Sants.  Entrance is free and visitors can wander around, talk about music or take along their records and exchange them or sell them, for recycling purposes or to allow others to enjoy the ones they don&#8217;t want.</p>
]]></content><date label="Quan:"><![CDATA[2014-10-27 16:49:39]]></date><thumbnail label="Destacat"><![CDATA[http://eldigital.bcn.cat/wp-content/uploads/2014/10/firadiscmusical.jpg]]></thumbnail><author label="Autor"><![CDATA[Jaume Recasens]]></author><categories label="Categories"><item label=""><![CDATA[Music]]></item></categories><tags label="Tags"></tags><video label="Video"><![CDATA[]]></video><language label="Idioma"><![CDATA[en]]></language><originalpost label="ID post original"><![CDATA[101006]]></originalpost><imgsmall label="Imatge petita"><![CDATA[http://eldigital.bcn.cat/wp-content/uploads/2014/10/firadiscmusical.jpg]]></imgsmall><imgmedium label="Imagte mitjana"><![CDATA[http://eldigital.bcn.cat/wp-content/uploads/2014/10/firadiscmusical-300x300.jpg]]></imgmedium><imglarge label="Imatge gran"><![CDATA[http://eldigital.bcn.cat/wp-content/uploads/2014/10/firadiscmusical.jpg]]></imglarge><imgtitle label=""><![CDATA[firadiscmusical]]></imgtitle><imgdesc label="Descripció de la imatge"><![CDATA[]]></imgdesc><imglleg label="LLegenda de la imatge"><![CDATA[]]></imglleg><imgalt label="Texte alternatiu de la imatge"><![CDATA[]]></imgalt><postidioma idioma="ca"><![CDATA[http://eldigital.bcn.cat/agenda/cita-amb-els-col%c2%b7leccionistes-musicals]]></postidioma><postidioma idioma="es"><![CDATA[http://eldigital.bcn.cat/es/agenda/cita-con-los-coleccionistas-musicales]]></postidioma><allimgsizes><thumbnail label=""><![CDATA[http://eldigital.bcn.cat/wp-content/uploads/2014/10/firadiscmusical-150x150.jpg]]></thumbnail><medium label=""><![CDATA[http://eldigital.bcn.cat/wp-content/uploads/2014/10/firadiscmusical-300x300.jpg]]></medium><large label=""><![CDATA[http://eldigital.bcn.cat/wp-content/uploads/2014/10/firadiscmusical-1024x768.jpg]]></large><post-image-mini label=""><![CDATA[http://eldigital.bcn.cat/wp-content/uploads/2014/10/firadiscmusical-50x50.jpg]]></post-image-mini><post-image-recom label=""><![CDATA[http://eldigital.bcn.cat/wp-content/uploads/2014/10/firadiscmusical-225x170.jpg]]></post-image-recom><post-image-square1 label=""><![CDATA[http://eldigital.bcn.cat/wp-content/uploads/2014/10/firadiscmusical-100x100.jpg]]></post-image-square1><post-image-square2 label=""><![CDATA[http://eldigital.bcn.cat/wp-content/uploads/2014/10/firadiscmusical-200x200.jpg]]></post-image-square2><post-image-panoramica2 label=""><![CDATA[http://eldigital.bcn.cat/wp-content/uploads/2014/10/firadiscmusical-190x107.jpg]]></post-image-panoramica2><post-image-col1 label=""><![CDATA[http://eldigital.bcn.cat/wp-content/uploads/2014/10/firadiscmusical-570x321.jpg]]></post-image-col1><post-image-col2 label=""><![CDATA[http://eldigital.bcn.cat/wp-content/uploads/2014/10/firadiscmusical-380x214.jpg]]></post-image-col2><post-image-panoramica label=""><![CDATA[http://eldigital.bcn.cat/wp-content/uploads/2014/10/firadiscmusical-760x428.jpg]]></post-image-panoramica><post-image-col3 label=""><![CDATA[http://eldigital.bcn.cat/wp-content/uploads/2014/10/firadiscmusical-280x158.jpg]]></post-image-col3></allimgsizes><videos></videos><imgsbodypost></imgsbodypost><gallery></gallery><related_post></related_post><attachments></attachments><moreinfo label="Més Informació"></moreinfo></detall>