<detall><id label=""><![CDATA[91090]]></id><title label="Titol"><![CDATA[Vine a viure la màgia de Disney al Teatre Borràs]]></title><excerpt label="Resum"><![CDATA[<strong>Teatre.</strong> La cantant Gisela protagonitza El libro mágico, un musical d’aventures en el qual haurà de superar 1.000 peripècies.]]></excerpt><content label="Contingut"><![CDATA[<p>El musical El libro mágico està protagonitzat per Gisela, la veu de Disney a l’estat espanyol. L’obra es pot veure al Teatre Borràs del 3 al 19 d’octubre. Sobre l’escenari hi ha altres rostres populars, com l’actiu Els Anka que fa el paper d’encantadora.</p>
<p>12 persones, un mag y uns ninotets completen el repartiment d’aquest fantàstic espectacle dirigit als més petits.</p>
]]></content><date label="Quan:"><![CDATA[2014-10-01 13:17:55]]></date><thumbnail label="Destacat"><![CDATA[http://eldigital.bcn.cat/wp-content/uploads/2014/10/disney.jpg]]></thumbnail><author label="Autor"><![CDATA[Cris Gibert]]></author><categories label="Categories"><item label=""><![CDATA[B cap de setmana]]></item></categories><tags label="Tags"></tags><video label="Video"><![CDATA[]]></video><language label="Idioma"><![CDATA[ca]]></language><originalpost label="ID post original"><![CDATA[91090]]></originalpost><imgsmall label="Imatge petita"><![CDATA[http://eldigital.bcn.cat/wp-content/uploads/2014/10/disney.jpg]]></imgsmall><imgmedium label="Imagte mitjana"><![CDATA[http://eldigital.bcn.cat/wp-content/uploads/2014/10/disney-300x300.jpg]]></imgmedium><imglarge label="Imatge gran"><![CDATA[http://eldigital.bcn.cat/wp-content/uploads/2014/10/disney.jpg]]></imglarge><imgtitle label=""><![CDATA[disney]]></imgtitle><imgdesc label="Descripció de la imatge"><![CDATA[]]></imgdesc><imglleg label="LLegenda de la imatge"><![CDATA[]]></imglleg><imgalt label="Texte alternatiu de la imatge"><![CDATA[]]></imgalt><allimgsizes><thumbnail label=""><![CDATA[http://eldigital.bcn.cat/wp-content/uploads/2014/10/disney-150x150.jpg]]></thumbnail><medium label=""><![CDATA[http://eldigital.bcn.cat/wp-content/uploads/2014/10/disney-300x300.jpg]]></medium><large label=""><![CDATA[http://eldigital.bcn.cat/wp-content/uploads/2014/10/disney.jpg]]></large><post-image-mini label=""><![CDATA[http://eldigital.bcn.cat/wp-content/uploads/2014/10/disney-50x50.jpg]]></post-image-mini><post-image-recom label=""><![CDATA[http://eldigital.bcn.cat/wp-content/uploads/2014/10/disney-225x170.jpg]]></post-image-recom><post-image-square1 label=""><![CDATA[http://eldigital.bcn.cat/wp-content/uploads/2014/10/disney-100x100.jpg]]></post-image-square1><post-image-square2 label=""><![CDATA[http://eldigital.bcn.cat/wp-content/uploads/2014/10/disney-200x200.jpg]]></post-image-square2><post-image-panoramica2 label=""><![CDATA[http://eldigital.bcn.cat/wp-content/uploads/2014/10/disney-190x107.jpg]]></post-image-panoramica2><post-image-col1 label=""><![CDATA[http://eldigital.bcn.cat/wp-content/uploads/2014/10/disney-570x321.jpg]]></post-image-col1><post-image-col2 label=""><![CDATA[http://eldigital.bcn.cat/wp-content/uploads/2014/10/disney-380x214.jpg]]></post-image-col2><post-image-panoramica label=""><![CDATA[http://eldigital.bcn.cat/wp-content/uploads/2014/10/disney-760x428.jpg]]></post-image-panoramica><post-image-col3 label=""><![CDATA[http://eldigital.bcn.cat/wp-content/uploads/2014/10/disney-280x158.jpg]]></post-image-col3></allimgsizes><videos></videos><imgsbodypost></imgsbodypost><gallery></gallery><related_post></related_post><attachments></attachments><moreinfo label="Més Informació"></moreinfo></detall>