<detall><id label=""><![CDATA[67325]]></id><title label="Titol"><![CDATA[Nit de Tango amb Mora Godoy]]></title><excerpt label="Resum"><![CDATA[La figura més destacada del tango argentí actual uneix la sensualitat del Raval i el llenguatge contemporani en un espectacle agosarat que combina tradició i avantguarda.]]></excerpt><content label="Contingut"><![CDATA[<p>Mora Godoy porta el millor tango al Grec. Mantenint l’essència tradicional del gènere i la sensualitat que transpira, Godoy ha renovat el tango atrevint-se a experimentar i creant una manera nova d’explicar històries mitjançant la dansa.</p>
<p>En aquest espectacle treballa sobre una fusió de tango i milonga amb candombe, música electrònica i salsa en escenes tangueres vibrants que busquen manllevar la malenconia del tango.</p>
]]></content><date label="Quan:"><![CDATA[2014-07-09 15:51:34]]></date><thumbnail label="Destacat"><![CDATA[http://eldigital.bcn.cat/wp-content/uploads/2014/07/tango.jpg]]></thumbnail><author label="Autor"><![CDATA[José María Dempere]]></author><categories label="Categories"></categories><tags label="Tags"><item label=""><![CDATA[agenda 500]]></item></tags><video label="Video"><![CDATA[]]></video><language label="Idioma"><![CDATA[ca]]></language><originalpost label="ID post original"><![CDATA[67325]]></originalpost><imgsmall label="Imatge petita"><![CDATA[http://eldigital.bcn.cat/wp-content/uploads/2014/07/tango.jpg]]></imgsmall><imgmedium label="Imagte mitjana"><![CDATA[http://eldigital.bcn.cat/wp-content/uploads/2014/07/tango-300x300.jpg]]></imgmedium><imglarge label="Imatge gran"><![CDATA[http://eldigital.bcn.cat/wp-content/uploads/2014/07/tango.jpg]]></imglarge><imgtitle label=""><![CDATA[tango]]></imgtitle><imgdesc label="Descripció de la imatge"><![CDATA[]]></imgdesc><imglleg label="LLegenda de la imatge"><![CDATA[]]></imglleg><imgalt label="Texte alternatiu de la imatge"><![CDATA[]]></imgalt><postidioma idioma="es"><![CDATA[http://eldigital.bcn.cat/?agenda=my-new-post-6132&amp;lang=es]]></postidioma><postidioma idioma="en"><![CDATA[http://eldigital.bcn.cat/?agenda=my-new-post-6133&amp;lang=en]]></postidioma><allimgsizes><thumbnail label=""><![CDATA[http://eldigital.bcn.cat/wp-content/uploads/2014/07/tango-150x150.jpg]]></thumbnail><medium label=""><![CDATA[http://eldigital.bcn.cat/wp-content/uploads/2014/07/tango-300x300.jpg]]></medium><large label=""><![CDATA[http://eldigital.bcn.cat/wp-content/uploads/2014/07/tango.jpg]]></large><post-image-mini label=""><![CDATA[http://eldigital.bcn.cat/wp-content/uploads/2014/07/tango-50x50.jpg]]></post-image-mini><post-image-recom label=""><![CDATA[http://eldigital.bcn.cat/wp-content/uploads/2014/07/tango-225x170.jpg]]></post-image-recom><post-image-square1 label=""><![CDATA[http://eldigital.bcn.cat/wp-content/uploads/2014/07/tango-100x100.jpg]]></post-image-square1><post-image-square2 label=""><![CDATA[http://eldigital.bcn.cat/wp-content/uploads/2014/07/tango-200x200.jpg]]></post-image-square2><post-image-panoramica2 label=""><![CDATA[http://eldigital.bcn.cat/wp-content/uploads/2014/07/tango-190x107.jpg]]></post-image-panoramica2><post-image-col1 label=""><![CDATA[http://eldigital.bcn.cat/wp-content/uploads/2014/07/tango-570x321.jpg]]></post-image-col1><post-image-col2 label=""><![CDATA[http://eldigital.bcn.cat/wp-content/uploads/2014/07/tango-380x214.jpg]]></post-image-col2><post-image-panoramica label=""><![CDATA[http://eldigital.bcn.cat/wp-content/uploads/2014/07/tango-760x428.jpg]]></post-image-panoramica><post-image-col3 label=""><![CDATA[http://eldigital.bcn.cat/wp-content/uploads/2014/07/tango-280x158.jpg]]></post-image-col3></allimgsizes><videos></videos><imgsbodypost></imgsbodypost><gallery></gallery><related_post></related_post><attachments></attachments></detall>