<detall><id label=""><![CDATA[36941]]></id><title label="Titol"><![CDATA["Celebrem el Dia Europeu dels Parcs: contes de natura"]]></title><excerpt label="Resum"><![CDATA[La Biblioteca Collserola - Josep Miracle celebra la primavera amb propostes plenes d’imaginació per a petits i grans.]]></excerpt><content label="Contingut"><![CDATA[<p>La Biblioteca Collserola &#8211; Josep Miracle celebra la primavera amb propostes plenes d’imaginació per a petits i grans.</p>
<p><b>El dimecres 21 de maig, a les 17.30 h. </b><b>&#8221; </b><b>Celebrem el Dia Europeu dels Parcs:</b> <b>contes de natura&#8221;</b><b>.</b> <b> </b>Sessió de contes en què els animals del Parc de Collserola seran els protagonistes i tots vosaltres us convertireu potser en un mussol, potser en una guineu o potser en un senglar.<b> </b>Veniu a ser els protagonistes del conte del Dia dels Parcs. A continuació es farà un mural sobre els animals i es penjarà a la biblioteca.</p>
<p>Sessió a càrrec de Vivi Lepori amb la col·laboració del Centre de Documentació i Recursos Educatius del Consorci del Parc de Collserola.</p>
<p><b>El dimecres 11 de juny, a les 19.00 h. </b><b>&#8220;Verdeguejar</b>. Viatge per la biografia de Jacint Verdaguer a través dels seus poemes&#8221;. A càrrec d&#8217;Anna Maluquer.</p>
<p><b>El dimecres 18 de juny, a les 17.30 h.</b> <b>&#8220;Contes de natura</b>: <b>comença l&#8217;estiu&#8221;.</b> El sol s&#8217;apropa, el dia s&#8217;escurça, la calor és forta, i per refrescar-nos la natura ens regala fruites fresques i la biblioteca contes a l&#8217;ombra. A càrrec de Vivi Lepori. Activitat gratuïta. No cal inscriure-s&#8217;hi prèviament.</p>
<p>Activitats gratuïtes. No cal inscriure-s&#8217;hi prèviament.</p>
<p>Biblioteca Collserola &#8211; Josep Miracle<br />
Biblioteques de Barcelona<br />
Reis Catòlics, 16-34</p>
  <!-- .photo-galleria -->
]]></content><date label="Quan:"><![CDATA[2014-04-24 15:35:40]]></date><thumbnail label="Destacat"><![CDATA[http://eldigital.bcn.cat/wp-content/uploads/2014/04/Parks_European_Day.jpg]]></thumbnail><author label="Autor"><![CDATA[Districte Sarrià-Sant Gervasi]]></author><categories label="Categories"><item label=""><![CDATA[Districte Sarrià-St.Gervasi]]></item></categories><tags label="Tags"><item label=""><![CDATA[biblioteca]]></item><item label=""><![CDATA[Collserola]]></item><item label=""><![CDATA[josep miracle]]></item><item label=""><![CDATA[verdaguer]]></item></tags><video label="Video"><![CDATA[]]></video><language label="Idioma"><![CDATA[ca]]></language><originalpost label="ID post original"><![CDATA[36941]]></originalpost><imgsmall label="Imatge petita"><![CDATA[http://eldigital.bcn.cat/wp-content/uploads/2014/04/Parks_European_Day-150x150.jpg]]></imgsmall><imgmedium label="Imagte mitjana"><![CDATA[http://eldigital.bcn.cat/wp-content/uploads/2014/04/Parks_European_Day-300x300.jpg]]></imgmedium><imglarge label="Imatge gran"><![CDATA[http://eldigital.bcn.cat/wp-content/uploads/2014/04/Parks_European_Day.jpg]]></imglarge><imgtitle label=""><![CDATA[Parks_European_Day]]></imgtitle><imgdesc label="Descripció de la imatge"><![CDATA[]]></imgdesc><imglleg label="LLegenda de la imatge"><![CDATA[]]></imglleg><imgalt label="Texte alternatiu de la imatge"><![CDATA[]]></imgalt><postidioma idioma="es"><![CDATA[http://eldigital.bcn.cat/?agenda=my-new-post-2449&amp;lang=es]]></postidioma><allimgsizes><thumbnail label=""><![CDATA[http://eldigital.bcn.cat/wp-content/uploads/2014/04/Parks_European_Day-150x150.jpg]]></thumbnail><medium label=""><![CDATA[http://eldigital.bcn.cat/wp-content/uploads/2014/04/Parks_European_Day-300x300.jpg]]></medium><large label=""><![CDATA[http://eldigital.bcn.cat/wp-content/uploads/2014/04/Parks_European_Day.jpg]]></large><post-image-mini label=""><![CDATA[http://eldigital.bcn.cat/wp-content/uploads/2014/04/Parks_European_Day-50x50.jpg]]></post-image-mini><post-image-col1 label=""><![CDATA[http://eldigital.bcn.cat/wp-content/uploads/2014/04/Parks_European_Day-343x193.jpg]]></post-image-col1><post-image-panoramica label=""><![CDATA[http://eldigital.bcn.cat/wp-content/uploads/2014/04/Parks_European_Day-550x364.jpg]]></post-image-panoramica><post-image-recom label=""><![CDATA[http://eldigital.bcn.cat/wp-content/uploads/2014/04/Parks_European_Day-225x170.jpg]]></post-image-recom><post-image-col2 label=""><![CDATA[http://eldigital.bcn.cat/wp-content/uploads/2014/04/Parks_European_Day-278x155.jpg]]></post-image-col2></allimgsizes><videos></videos><imgsbodypost><item label=""><![CDATA[<img width="150" height="150" src="http://eldigital.bcn.cat/wp-content/uploads/2014/04/Parks_European_Day-150x150.jpg" class="attachment-thumbnail" alt="Parks_European_Day" />]]></item></imgsbodypost><gallery><item label=""><![CDATA[<div class='photo-galleria' >
		<style type='text/css'>
			#gallery-1 {
				margin: auto;
			}
			#gallery-1 .gallery-item {
				float: left;
				margin-top: 10px;
				text-align: center;
				width: 33%;
			}
			#gallery-1 img {
				border: 2px solid #cfcfcf;
			}
			#gallery-1 .gallery-caption {
				margin-left: 0;
			}
		</style>
		<!-- see gallery_shortcode() in wp-includes/media.php -->
		<div id='gallery-1' class='gallery galleryid-36941 gallery-columns-3 gallery-size-thumbnail'><dl class='gallery-item'>
			<dt class='gallery-icon'>
				<a href='http://eldigital.bcn.cat/wp-content/uploads/2014/04/Parks_European_Day.jpg' title='Parks_European_Day'><img width="150" height="150" src="http://eldigital.bcn.cat/wp-content/uploads/2014/04/Parks_European_Day-150x150.jpg" class="attachment-thumbnail" alt="Parks_European_Day" /></a>
			</dt></dl>
			<br style='clear: both;' />
		</div></div>]]></item></gallery><related_post></related_post><attachments></attachments></detall>