<detall><id label=""><![CDATA[37972]]></id><title label="Titol"><![CDATA[Barcelona, sortida i arribada de la primera CicloVolta]]></title><excerpt label="Resum"><![CDATA[<strong>Esports.</strong> Amb un recorregut de gairebé 500 quilòmetres, la ruta passarà per nou comarques i travessarà ports mítics de la geografia catalana.]]></excerpt><content label="Contingut"><![CDATA[<p>La primera edició de la CicloVolta a Catalunya consta de quatre etapes, amb sortida i arribada a Barcelona. En la primera d’elles, la ruta bordeja la costa per la serralada de Marina fins a Sant Celoni, amb 26 quilòmetres d’ascensió pel Parc Natural del Montseny.</p>
<p>La CicloVolta, que travessa nou comarques catalanes, finalitza a la muntanya de Collserola, amb pujades properes al 20% i amb un últim traçat opcional cap al Forat del Vent.</p>
]]></content><date label="Quan:"><![CDATA[2014-04-30 08:00:52]]></date><thumbnail label="Destacat"><![CDATA[http://eldigital.bcn.cat/wp-content/uploads/2014/04/ciclovolta.jpg]]></thumbnail><author label="Autor"><![CDATA[Redacció bcn.cat]]></author><categories label="Categories"><item label=""><![CDATA[Esports]]></item><item label=""><![CDATA[B cap de setmana]]></item><item label=""><![CDATA[Oci]]></item><item label=""><![CDATA[Home bcn.cat]]></item></categories><tags label="Tags"></tags><video label="Video"><![CDATA[]]></video><language label="Idioma"><![CDATA[ca]]></language><originalpost label="ID post original"><![CDATA[37972]]></originalpost><imgsmall label="Imatge petita"><![CDATA[http://eldigital.bcn.cat/wp-content/uploads/2014/04/ciclovolta-150x150.jpg]]></imgsmall><imgmedium label="Imagte mitjana"><![CDATA[http://eldigital.bcn.cat/wp-content/uploads/2014/04/ciclovolta-300x300.jpg]]></imgmedium><imglarge label="Imatge gran"><![CDATA[http://eldigital.bcn.cat/wp-content/uploads/2014/04/ciclovolta.jpg]]></imglarge><imgtitle label=""><![CDATA[ciclovolta]]></imgtitle><imgdesc label="Descripció de la imatge"><![CDATA[]]></imgdesc><imglleg label="LLegenda de la imatge"><![CDATA[]]></imglleg><imgalt label="Texte alternatiu de la imatge"><![CDATA[]]></imgalt><allimgsizes><thumbnail label=""><![CDATA[http://eldigital.bcn.cat/wp-content/uploads/2014/04/ciclovolta-150x150.jpg]]></thumbnail><medium label=""><![CDATA[http://eldigital.bcn.cat/wp-content/uploads/2014/04/ciclovolta-300x300.jpg]]></medium><large label=""><![CDATA[http://eldigital.bcn.cat/wp-content/uploads/2014/04/ciclovolta.jpg]]></large><post-image-mini label=""><![CDATA[http://eldigital.bcn.cat/wp-content/uploads/2014/04/ciclovolta-50x50.jpg]]></post-image-mini><post-image-col1 label=""><![CDATA[http://eldigital.bcn.cat/wp-content/uploads/2014/04/ciclovolta-343x193.jpg]]></post-image-col1><post-image-panoramica label=""><![CDATA[http://eldigital.bcn.cat/wp-content/uploads/2014/04/ciclovolta-641x364.jpg]]></post-image-panoramica><post-image-recom label=""><![CDATA[http://eldigital.bcn.cat/wp-content/uploads/2014/04/ciclovolta-225x170.jpg]]></post-image-recom><post-image-col2 label=""><![CDATA[http://eldigital.bcn.cat/wp-content/uploads/2014/04/ciclovolta-278x155.jpg]]></post-image-col2></allimgsizes><videos></videos><imgsbodypost></imgsbodypost><gallery></gallery><related_post></related_post><attachments></attachments></detall>