<detall><id label=""><![CDATA[77761]]></id><title label="Titol"><![CDATA[The International Open Chess Tournament of Sants, Hostafrancs and la Bordeta is back]]></title><excerpt label="Resum"><![CDATA[The tournament will be held at the Auditori del Centre Cívic Cotxeres in Sants from 22 to 31 August.]]></excerpt><content label="Contingut"><![CDATA[<p>This month of August, chess takes on the leading role in the celebration of the International Open Chess Tournament of Sants, Hostafrancs and la Bordeta, a classic summer event that gathers some of the best tacticians of the game.</p>
<p>The tournament will be held at the Auditori del Centre Cívic Cotxeres in Sants. It is valid for the Catalan Circuit of group A and forms part of the Sants Festival.</p>
]]></content><date label="Quan:"><![CDATA[2014-08-19 12:50:18]]></date><thumbnail label="Destacat"><![CDATA[http://eldigital.bcn.cat/wp-content/uploads/2014/08/escacs.jpg]]></thumbnail><author label="Autor"><![CDATA[José María Dempere]]></author><categories label="Categories"></categories><tags label="Tags"></tags><video label="Video"><![CDATA[]]></video><language label="Idioma"><![CDATA[en]]></language><originalpost label="ID post original"><![CDATA[77680]]></originalpost><imgsmall label="Imatge petita"><![CDATA[http://eldigital.bcn.cat/wp-content/uploads/2014/08/escacs.jpg]]></imgsmall><imgmedium label="Imagte mitjana"><![CDATA[http://eldigital.bcn.cat/wp-content/uploads/2014/08/escacs-300x300.jpg]]></imgmedium><imglarge label="Imatge gran"><![CDATA[http://eldigital.bcn.cat/wp-content/uploads/2014/08/escacs.jpg]]></imglarge><imgtitle label=""><![CDATA[escacs]]></imgtitle><imgdesc label="Descripció de la imatge"><![CDATA[]]></imgdesc><imglleg label="LLegenda de la imatge"><![CDATA[]]></imglleg><imgalt label="Texte alternatiu de la imatge"><![CDATA[]]></imgalt><postidioma idioma="ca"><![CDATA[http://eldigital.bcn.cat/?agenda=torna-lopen-internacional-descacs-de-sants-hostafrancs-i-la-bordeta]]></postidioma><postidioma idioma="es"><![CDATA[http://eldigital.bcn.cat/?agenda=vuelve-el-open-internacional-de-ajedrez-de-sants-hostafrancs-y-la-bordeta&amp;lang=es]]></postidioma><allimgsizes><thumbnail label=""><![CDATA[http://eldigital.bcn.cat/wp-content/uploads/2014/08/escacs-150x150.jpg]]></thumbnail><medium label=""><![CDATA[http://eldigital.bcn.cat/wp-content/uploads/2014/08/escacs-300x300.jpg]]></medium><large label=""><![CDATA[http://eldigital.bcn.cat/wp-content/uploads/2014/08/escacs.jpg]]></large><post-image-mini label=""><![CDATA[http://eldigital.bcn.cat/wp-content/uploads/2014/08/escacs-50x50.jpg]]></post-image-mini><post-image-recom label=""><![CDATA[http://eldigital.bcn.cat/wp-content/uploads/2014/08/escacs-225x170.jpg]]></post-image-recom><post-image-square1 label=""><![CDATA[http://eldigital.bcn.cat/wp-content/uploads/2014/08/escacs-100x100.jpg]]></post-image-square1><post-image-square2 label=""><![CDATA[http://eldigital.bcn.cat/wp-content/uploads/2014/08/escacs-200x200.jpg]]></post-image-square2><post-image-panoramica2 label=""><![CDATA[http://eldigital.bcn.cat/wp-content/uploads/2014/08/escacs-190x107.jpg]]></post-image-panoramica2><post-image-col1 label=""><![CDATA[http://eldigital.bcn.cat/wp-content/uploads/2014/08/escacs-570x321.jpg]]></post-image-col1><post-image-col2 label=""><![CDATA[http://eldigital.bcn.cat/wp-content/uploads/2014/08/escacs-380x214.jpg]]></post-image-col2><post-image-panoramica label=""><![CDATA[http://eldigital.bcn.cat/wp-content/uploads/2014/08/escacs-760x428.jpg]]></post-image-panoramica><post-image-col3 label=""><![CDATA[http://eldigital.bcn.cat/wp-content/uploads/2014/08/escacs-280x158.jpg]]></post-image-col3></allimgsizes><videos></videos><imgsbodypost></imgsbodypost><gallery></gallery><related_post></related_post><attachments></attachments></detall>