<detall><id label=""><![CDATA[56066]]></id><title label="Titol"><![CDATA[El mar de Sorolla]]></title><excerpt label="Resum"><![CDATA[<strong>Exposiciones.</strong> El CaixaForum expone &quot;Sorolla. El color del mar&quot;, una muestra que evidencia la clara pasión del artista por el universo marino.]]></excerpt><content label="Contingut"><![CDATA[<p>El mar fue el tema más popular del artista Joaquín Sorolla. Es por eso por lo que el CaixaForum dedica una exposición a esta temática. Las obras, formadas por lienzos y pequeñas notas de color en los que el artista tomaba apuntes, reflejan la particular manera del pintor de analizar la naturaleza y utilizar los colores. La exposición se desarrolla en tres secciones: &#8220;El espectáculo incesante&#8221;, &#8220;Las horas del azul&#8221; y &#8220;De la naturaleza a la pintura&#8221;, y plantea a los visitantes preguntas como: &#8220;¿De qué color es el mar?&#8221;. ¡No te la pierdas!</p>
<p>&nbsp;</p>
]]></content><date label="Quan:"><![CDATA[2014-06-14 08:00:58]]></date><thumbnail label="Destacat"><![CDATA[http://eldigital.bcn.cat/wp-content/uploads/2014/06/ed64d0a5f9c9e02f700540343d239d5e.jpg]]></thumbnail><author label="Autor"><![CDATA[Redacció bcn.cat]]></author><categories label="Categories"><item label=""><![CDATA[Cultura]]></item><item label=""><![CDATA[B Fin de semana]]></item></categories><tags label="Tags"></tags><video label="Video"><![CDATA[http://youtu.be/LojwakTAwW4]]></video><language label="Idioma"><![CDATA[es]]></language><originalpost label="ID post original"><![CDATA[55976]]></originalpost><imgsmall label="Imatge petita"><![CDATA[http://eldigital.bcn.cat/wp-content/uploads/2014/06/ed64d0a5f9c9e02f700540343d239d5e-150x150.jpg]]></imgsmall><imgmedium label="Imagte mitjana"><![CDATA[http://eldigital.bcn.cat/wp-content/uploads/2014/06/ed64d0a5f9c9e02f700540343d239d5e-300x300.jpg]]></imgmedium><imglarge label="Imatge gran"><![CDATA[http://eldigital.bcn.cat/wp-content/uploads/2014/06/ed64d0a5f9c9e02f700540343d239d5e.jpg]]></imglarge><imgtitle label=""><![CDATA[sorolla exposició]]></imgtitle><imgdesc label="Descripció de la imatge"><![CDATA[caixaforum]]></imgdesc><imglleg label="LLegenda de la imatge"><![CDATA[]]></imglleg><imgalt label="Texte alternatiu de la imatge"><![CDATA[]]></imgalt><postidioma idioma="ca"><![CDATA[http://eldigital.bcn.cat/?agenda=el-mar-de-sorolla]]></postidioma><postidioma idioma="en"><![CDATA[http://eldigital.bcn.cat/?agenda=my-new-post-4775&amp;lang=en]]></postidioma><allimgsizes><thumbnail label=""><![CDATA[http://eldigital.bcn.cat/wp-content/uploads/2014/06/ed64d0a5f9c9e02f700540343d239d5e-150x150.jpg]]></thumbnail><medium label=""><![CDATA[http://eldigital.bcn.cat/wp-content/uploads/2014/06/ed64d0a5f9c9e02f700540343d239d5e-300x300.jpg]]></medium><large label=""><![CDATA[http://eldigital.bcn.cat/wp-content/uploads/2014/06/ed64d0a5f9c9e02f700540343d239d5e.jpg]]></large><post-image-mini label=""><![CDATA[http://eldigital.bcn.cat/wp-content/uploads/2014/06/ed64d0a5f9c9e02f700540343d239d5e-50x50.jpg]]></post-image-mini><post-image-recom label=""><![CDATA[http://eldigital.bcn.cat/wp-content/uploads/2014/06/ed64d0a5f9c9e02f700540343d239d5e-225x170.jpg]]></post-image-recom><post-image-square1 label=""><![CDATA[http://eldigital.bcn.cat/wp-content/uploads/2014/06/ed64d0a5f9c9e02f700540343d239d5e-100x100.jpg]]></post-image-square1><post-image-square2 label=""><![CDATA[http://eldigital.bcn.cat/wp-content/uploads/2014/06/ed64d0a5f9c9e02f700540343d239d5e-200x200.jpg]]></post-image-square2><post-image-panoramica2 label=""><![CDATA[http://eldigital.bcn.cat/wp-content/uploads/2014/06/ed64d0a5f9c9e02f700540343d239d5e-190x107.jpg]]></post-image-panoramica2><post-image-col1 label=""><![CDATA[http://eldigital.bcn.cat/wp-content/uploads/2014/06/ed64d0a5f9c9e02f700540343d239d5e-570x321.jpg]]></post-image-col1><post-image-col2 label=""><![CDATA[http://eldigital.bcn.cat/wp-content/uploads/2014/06/ed64d0a5f9c9e02f700540343d239d5e-380x214.jpg]]></post-image-col2><post-image-panoramica label=""><![CDATA[http://eldigital.bcn.cat/wp-content/uploads/2014/06/ed64d0a5f9c9e02f700540343d239d5e-760x428.jpg]]></post-image-panoramica><post-image-col3 label=""><![CDATA[http://eldigital.bcn.cat/wp-content/uploads/2014/06/ed64d0a5f9c9e02f700540343d239d5e-280x158.jpg]]></post-image-col3></allimgsizes><videos></videos><imgsbodypost></imgsbodypost><gallery></gallery><related_post></related_post><attachments></attachments></detall>