<detall><id label=""><![CDATA[27421]]></id><title label="Titol"><![CDATA[A family outing to the Centre de la Platja]]></title><excerpt label="Resum"><![CDATA[<strong>Leisure.</strong> Find out about the family activities organised by the <em>Centre de la Platja </em>on marine biodiversity and the sea.]]></excerpt><content label="Contingut"><![CDATA[<p>The Centre de la Platja [The Beach Centre] organises activities for the whole family from March until the end of August.</p>
<p>For example, you can find out about marine diversity at the De la platja al Zoo: Els tresors de la Mediterrània [From the beach to the zoo: the jewels of the Mediterranean] workshop , which includes educational sessions with dolphins and a day&#8217;s entrance to Barcelona Zoo. You can also join in with the QR-code gymkhana Descodificant el mar [Decoding the Sea], the crafts workshop and the interactive competition about the Parc dels Esculls, and the El bateig de Neptú [Baptism of Neptune], to discover the Barcelona Maritime Museum.</p>
]]></content><date label="Quan:"><![CDATA[2014-04-08 07:00:41]]></date><thumbnail label="Destacat"><![CDATA[http://eldigital.bcn.cat/wp-content/uploads/2014/04/centreplatja1.jpg]]></thumbnail><author label="Autor"><![CDATA[Redacció bcn.cat]]></author><categories label="Categories"><item label=""><![CDATA[B Weekend]]></item><item label=""><![CDATA[Children]]></item><item label=""><![CDATA[Leisure]]></item><item label=""><![CDATA[Routes]]></item></categories><tags label="Tags"></tags><video label="Video"><![CDATA[]]></video><language label="Idioma"><![CDATA[en]]></language><originalpost label="ID post original"><![CDATA[27105]]></originalpost><imgsmall label="Imatge petita"><![CDATA[http://eldigital.bcn.cat/wp-content/uploads/2014/04/centreplatja1-150x150.jpg]]></imgsmall><imgmedium label="Imagte mitjana"><![CDATA[http://eldigital.bcn.cat/wp-content/uploads/2014/04/centreplatja1-300x300.jpg]]></imgmedium><imglarge label="Imatge gran"><![CDATA[http://eldigital.bcn.cat/wp-content/uploads/2014/04/centreplatja1.jpg]]></imglarge><imgtitle label=""><![CDATA[Centre de la Platja]]></imgtitle><imgdesc label="Descripció de la imatge"><![CDATA[Centre de la Platja]]></imgdesc><imglleg label="LLegenda de la imatge"><![CDATA[Centre de la Platja]]></imglleg><imgalt label="Texte alternatiu de la imatge"><![CDATA[]]></imgalt><postidioma idioma="ca"><![CDATA[http://eldigital.bcn.cat/?agenda=al-centre-de-la-platja-en-familia]]></postidioma><postidioma idioma="es"><![CDATA[http://eldigital.bcn.cat/?agenda=my-new-post-1794&amp;lang=es]]></postidioma><allimgsizes><thumbnail label=""><![CDATA[http://eldigital.bcn.cat/wp-content/uploads/2014/04/centreplatja1-150x150.jpg]]></thumbnail><medium label=""><![CDATA[http://eldigital.bcn.cat/wp-content/uploads/2014/04/centreplatja1-300x300.jpg]]></medium><large label=""><![CDATA[http://eldigital.bcn.cat/wp-content/uploads/2014/04/centreplatja1.jpg]]></large><post-image-mini label=""><![CDATA[http://eldigital.bcn.cat/wp-content/uploads/2014/04/centreplatja1-50x50.jpg]]></post-image-mini><post-image-recom label=""><![CDATA[http://eldigital.bcn.cat/wp-content/uploads/2014/04/centreplatja1-225x170.jpg]]></post-image-recom><post-image-square1 label=""><![CDATA[http://eldigital.bcn.cat/wp-content/uploads/2014/04/centreplatja1-100x100.jpg]]></post-image-square1><post-image-square2 label=""><![CDATA[http://eldigital.bcn.cat/wp-content/uploads/2014/04/centreplatja1-200x200.jpg]]></post-image-square2><post-image-panoramica2 label=""><![CDATA[http://eldigital.bcn.cat/wp-content/uploads/2014/04/centreplatja1-190x107.jpg]]></post-image-panoramica2><post-image-col1 label=""><![CDATA[http://eldigital.bcn.cat/wp-content/uploads/2014/04/centreplatja1-570x321.jpg]]></post-image-col1><post-image-col2 label=""><![CDATA[http://eldigital.bcn.cat/wp-content/uploads/2014/04/centreplatja1-380x214.jpg]]></post-image-col2><post-image-panoramica label=""><![CDATA[http://eldigital.bcn.cat/wp-content/uploads/2014/04/centreplatja1-760x428.jpg]]></post-image-panoramica><post-image-col3 label=""><![CDATA[http://eldigital.bcn.cat/wp-content/uploads/2014/04/centreplatja1.jpg]]></post-image-col3></allimgsizes><videos></videos><imgsbodypost></imgsbodypost><gallery></gallery><related_post></related_post><attachments></attachments></detall>