<detall><id label=""><![CDATA[10034]]></id><title label="Titol"><![CDATA[Els millors temes de cine, orquestrats]]></title><excerpt label="Resum"><![CDATA[<strong>Música.</strong> La Cinema Symphony Orchestra porta al Palau de la Música bandes sonores inoblidables, com les d’E.T., West Side Story o Jurassic Park.]]></excerpt><content label="Contingut"><![CDATA[<p>Hi ha bandes sonores de pel·lícules que ens marquen tant com les imatges que acompanyen. Ara, podreu escoltar-les en directe, amb la Cinema Symphony Orchestra, que ofereix un concert al Palau de la Música amb peces tan inoblidables com les d’<i>E.T.</i>, <i>West Side Story</i>, <i>Piratas del Caribe</i>, <i>La llista de Schindler</i> o <i>Jurassic Park</i>, entre moltes altres.</p>
  <!-- .photo-galleria -->
]]></content><date label="Quan:"><![CDATA[2014-01-13 12:08:32]]></date><thumbnail label="Destacat"><![CDATA[http://eldigital.bcn.cat/wp-content/uploads/2014/01/cinemaorquestra.jpg]]></thumbnail><author label="Autor"><![CDATA[Verònica Heredia]]></author><categories label="Categories"><item label=""><![CDATA[Cultura]]></item><item label=""><![CDATA[Espectacles]]></item><item label=""><![CDATA[Música]]></item></categories><tags label="Tags"><item label=""><![CDATA[palau de la música]]></item><item label=""><![CDATA[orquestra]]></item><item label=""><![CDATA[cinema]]></item><item label=""><![CDATA[symphony]]></item></tags><video label="Video"><![CDATA[]]></video><language label="Idioma"><![CDATA[ca]]></language><originalpost label="ID post original"><![CDATA[10034]]></originalpost><imgsmall label="Imatge petita"><![CDATA[http://eldigital.bcn.cat/wp-content/uploads/2014/01/cinemaorquestra-150x150.jpg]]></imgsmall><imgmedium label="Imagte mitjana"><![CDATA[http://eldigital.bcn.cat/wp-content/uploads/2014/01/cinemaorquestra-300x300.jpg]]></imgmedium><imglarge label="Imatge gran"><![CDATA[http://eldigital.bcn.cat/wp-content/uploads/2014/01/cinemaorquestra.jpg]]></imglarge><imgtitle label=""><![CDATA[cinemaorquestra]]></imgtitle><imgdesc label="Descripció de la imatge"><![CDATA[]]></imgdesc><imglleg label="LLegenda de la imatge"><![CDATA[]]></imglleg><imgalt label="Texte alternatiu de la imatge"><![CDATA[]]></imgalt><allimgsizes><thumbnail label=""><![CDATA[http://eldigital.bcn.cat/wp-content/uploads/2014/01/cinemaorquestra-150x150.jpg]]></thumbnail><medium label=""><![CDATA[http://eldigital.bcn.cat/wp-content/uploads/2014/01/cinemaorquestra-300x300.jpg]]></medium><large label=""><![CDATA[http://eldigital.bcn.cat/wp-content/uploads/2014/01/cinemaorquestra.jpg]]></large><post-image-mini label=""><![CDATA[http://eldigital.bcn.cat/wp-content/uploads/2014/01/cinemaorquestra-50x50.jpg]]></post-image-mini><post-image-col1 label=""><![CDATA[http://eldigital.bcn.cat/wp-content/uploads/2014/01/cinemaorquestra-343x193.jpg]]></post-image-col1><post-image-panoramica label=""><![CDATA[http://eldigital.bcn.cat/wp-content/uploads/2014/01/cinemaorquestra-641x364.jpg]]></post-image-panoramica><post-image-recom label=""><![CDATA[http://eldigital.bcn.cat/wp-content/uploads/2014/01/cinemaorquestra-225x170.jpg]]></post-image-recom><post-image-col2 label=""><![CDATA[http://eldigital.bcn.cat/wp-content/uploads/2014/01/cinemaorquestra-278x155.jpg]]></post-image-col2></allimgsizes><videos></videos><imgsbodypost><item label=""><![CDATA[<img width="150" height="150" src="http://eldigital.bcn.cat/wp-content/uploads/2014/01/cinemaorquestra-150x150.jpg" class="attachment-thumbnail" alt="cinemaorquestra" />]]></item></imgsbodypost><gallery><item label=""><![CDATA[<div class='photo-galleria' >
		<style type='text/css'>
			#gallery-1 {
				margin: auto;
			}
			#gallery-1 .gallery-item {
				float: left;
				margin-top: 10px;
				text-align: center;
				width: 33%;
			}
			#gallery-1 img {
				border: 2px solid #cfcfcf;
			}
			#gallery-1 .gallery-caption {
				margin-left: 0;
			}
		</style>
		<!-- see gallery_shortcode() in wp-includes/media.php -->
		<div id='gallery-1' class='gallery galleryid-10034 gallery-columns-3 gallery-size-thumbnail'><dl class='gallery-item'>
			<dt class='gallery-icon'>
				<a href='http://eldigital.bcn.cat/wp-content/uploads/2014/01/cinemaorquestra.jpg' title='cinemaorquestra'><img width="150" height="150" src="http://eldigital.bcn.cat/wp-content/uploads/2014/01/cinemaorquestra-150x150.jpg" class="attachment-thumbnail" alt="cinemaorquestra" /></a>
			</dt></dl>
			<br style='clear: both;' />
		</div></div>]]></item></gallery><related_post></related_post><attachments></attachments></detall>